InfluenceDiffusion/Graph.py
InfluenceDiffusion/Inference.py
InfluenceDiffusion/Trace.py
InfluenceDiffusion/__init__.py
InfluenceDiffusion/influence_models.py
InfluenceDiffusion/plot_utils.py
InfluenceDiffusion/utils.py
InfluenceDiffusion/weight_samplers.py
InfluenceDiffusion/estimation_models/BaseWeightEstimator.py
InfluenceDiffusion/estimation_models/CDFEstimation.py
InfluenceDiffusion/estimation_models/EMEstimation.py
InfluenceDiffusion/estimation_models/OptimEstimation.py
InfluenceDiffusion/estimation_models/__init__.py
influencediffusion-0.0.18.dist-info/licenses/LICENSE
influencediffusion-0.0.18.dist-info/METADATA
influencediffusion-0.0.18.dist-info/WHEEL
influencediffusion-0.0.18.dist-info/top_level.txt
influencediffusion-0.0.18.dist-info/RECORD
