Metadata-Version: 2.4
Name: InfluenceDiffusion
Version: 0.0.18
Summary: InfluenceDiffusion package
Author: Alexander Kagan
Author-email: <amkagan@umich.edu>
Keywords: python,Influence Maximization,Network diffusion models,General Linear Threshold model,Social Networks,Independent Cascade model
Classifier: Development Status :: 3 - Alpha
Classifier: Intended Audience :: Education
Classifier: Programming Language :: Python :: 2
Classifier: Programming Language :: Python :: 3
Classifier: Operating System :: MacOS :: MacOS X
Classifier: Operating System :: Microsoft :: Windows
License-File: LICENSE
Requires-Dist: numpy<2
Requires-Dist: scipy
Requires-Dist: networkx
Requires-Dist: typing
Requires-Dist: joblib
Dynamic: author
Dynamic: author-email
Dynamic: classifier
Dynamic: description
Dynamic: description-content-type
Dynamic: keywords
Dynamic: license-file
Dynamic: requires-dist
Dynamic: summary
